docs2md/__init__.py
docs2md/__main__.py
docs2md/docs2md.py
docs2md-1.0.1.dist-info/LICENSE
docs2md-1.0.1.dist-info/METADATA
docs2md-1.0.1.dist-info/WHEEL
docs2md-1.0.1.dist-info/top_level.txt
docs2md-1.0.1.dist-info/RECORD
