Metadata-Version: 2.1
Name: docs2md
Version: 1.0.1
Summary: Automatically parse python docstrings and convert them to markdown!
Home-page: https://github.com/JoaquimEsteves/docs-to-md
Author: Joaquim Esteves
Author-email: joaquimbve@hotmail.com
License: GPLv3+
Platform: UNKNOWN
Classifier: Programming Language :: Python :: 3
Classifier: License :: OSI Approved :: GNU General Public License v3 or later (GPLv3+)
Classifier: Operating System :: OS Independent
Requires-Python: >=3.6
